meilisearch_cli/__init__.py
meilisearch_cli/__main__.py
meilisearch_cli/_config.py
meilisearch_cli/_docs.py
meilisearch_cli/_helpers.py
meilisearch_cli/documents.py
meilisearch_cli/dump.py
meilisearch_cli/index.py
meilisearch_cli/main.py
meilisearch_cli/py.typed
meilisearch_cli-0.11.0.dist-info/entry_points.txt
meilisearch_cli-0.11.0.dist-info/LICENSE
meilisearch_cli-0.11.0.dist-info/WHEEL
meilisearch_cli-0.11.0.dist-info/METADATA
meilisearch_cli-0.11.0.dist-info/RECORD
