Metadata-Version: 2.1
Name: meilisearch-cli
Version: 0.11.0
Summary: CLI for MeiliSearch
Home-page: https://github.com/sanders41/meilisearch-cli
License: MIT
Keywords: meilisearch,cli
Author: Paul Sanders
Author-email: psanders1@gmail.com
Requires-Python: >=3.7,<4.0
Classifier: License :: OSI Approved :: MIT License
Classifier: Operating System :: OS Independent
Classifier: Programming Language :: Python :: 3
Classifier: Programming Language :: Python :: 3.10
Classifier: Programming Language :: Python :: 3.7
Classifier: Programming Language :: Python :: 3.8
Classifier: Programming Language :: Python :: 3.9
Requires-Dist: beautifulsoup4 (==4.11.1)
Requires-Dist: meilisearch (>=0.18.3,<0.19.0)
Requires-Dist: requests (==2.27.1)
Requires-Dist: rich (==12.4.1)
Requires-Dist: typer (==0.4.1)
Project-URL: Documentation, https://github.com/sanders41/meilisearch-cli
Project-URL: Repository, https://github.com/sanders41/meilisearch-cli
